xuml_populate/__init__.py
xuml_populate/__main__.py
xuml_populate/config.py
xuml_populate/log.conf
xuml_populate/system.py
xuml_populate/exceptions/__init__.py
xuml_populate/exceptions/action_exceptions.py
xuml_populate/exceptions/class_exceptions.py
xuml_populate/exceptions/mp_exceptions.py
xuml_populate/populate/__init__.py
xuml_populate/populate/activity.py
xuml_populate/populate/attribute.py
xuml_populate/populate/binary_association.py
xuml_populate/populate/domain.py
xuml_populate/populate/ee.py
xuml_populate/populate/element.py
xuml_populate/populate/flow.py
xuml_populate/populate/generalization.py
xuml_populate/populate/lineage.py
xuml_populate/populate/method.py
xuml_populate/populate/method_activity.py
xuml_populate/populate/mm_class.py
xuml_populate/populate/mm_type.py
xuml_populate/populate/mmclass_nt.py
xuml_populate/populate/mmdb.ral
xuml_populate/populate/ns_flow.py
xuml_populate/populate/operation.py
xuml_populate/populate/ordinal.py
xuml_populate/populate/reference.py
xuml_populate/populate/relationship.py
xuml_populate/populate/signature.py
xuml_populate/populate/state_model.py
xuml_populate/populate/statement.py
xuml_populate/populate/subsystem.py
xuml_populate/populate/synch_output.py
xuml_populate/populate/xunit.py
xuml_populate/populate/actions/__init__.py
xuml_populate/populate/actions/action.py
xuml_populate/populate/actions/aparse_types.py
xuml_populate/populate/actions/extract_action.py
xuml_populate/populate/actions/hop_types.py
xuml_populate/populate/actions/instance_assignment.py
xuml_populate/populate/actions/project_action.py
xuml_populate/populate/actions/rank_restrict_action.py
xuml_populate/populate/actions/read_action.py
xuml_populate/populate/actions/rename_action.py
xuml_populate/populate/actions/restrict_action.py
xuml_populate/populate/actions/scalar_assignment.py
xuml_populate/populate/actions/select_action.py
xuml_populate/populate/actions/set_action.py
xuml_populate/populate/actions/switch_action.py
xuml_populate-0.5.0.dist-info/licenses/LICENSE
xuml_populate-0.5.0.dist-info/METADATA
xuml_populate-0.5.0.dist-info/WHEEL
xuml_populate-0.5.0.dist-info/entry_points.txt
xuml_populate-0.5.0.dist-info/top_level.txt
xuml_populate-0.5.0.dist-info/RECORD
